QrEngineerSDK/QProviderFactory.py
QrEngineerSDK/__init__.py
QrEngineerSDK/objects/QrCircuitExecutionResult.py
QrEngineerSDK/objects/QrGates.py
QrEngineerSDK/objects/QrInstruction.py
QrEngineerSDK/objects/__init__.py
QrEngineerSDK/providers/QrAmazonBraketManager.py
QrEngineerSDK/providers/QrCirqManager.py
QrEngineerSDK/providers/QrDwaveManager.py
QrEngineerSDK/providers/QrQiskitManager.py
QrEngineerSDK/providers/__init__.py
QrEngineerSDK-1.0.2.dist-info/METADATA
QrEngineerSDK-1.0.2.dist-info/WHEEL
QrEngineerSDK-1.0.2.dist-info/top_level.txt
QrEngineerSDK-1.0.2.dist-info/RECORD
