Metadata-Version: 2.1
Name: QrEngineerSDK
Version: 1.0.2
Summary: QApps QrEngineer Python SDK
Home-page: https://core.quantumpath.app/qappsrengineer/
Author: QuantumPath
Keywords: quantum,quantumpath,qSOA,sdk,quantum applications,quantum software,qapps,qrengineer,transpilation
Classifier: Topic :: Scientific/Engineering
Classifier: Topic :: Software Development
Classifier: Development Status :: 5 - Production/Stable
Classifier: License :: Freely Distributable
Classifier: License :: Other/Proprietary License
Classifier: Programming Language :: Python :: 3
Classifier: Operating System :: OS Independent
Classifier: Intended Audience :: Developers
Classifier: Intended Audience :: Education
Classifier: Intended Audience :: Information Technology
Requires-Dist: QuantumPathQSOAPySDK
Requires-Dist: matplotlib
